treet/__init__.py
treet/parse.py
treet/reduce.py
treet/traverse.py
treet-1.0.5.dist-info/LICENSE
treet-1.0.5.dist-info/METADATA
treet-1.0.5.dist-info/WHEEL
treet-1.0.5.dist-info/top_level.txt
treet-1.0.5.dist-info/RECORD
