Metadata-Version: 2.1
Name: treet
Version: 1.0.5
Summary: Simple, minimal, but powerful tools to handle any kind of hierarchical (tree) structures
Home-page: https://github.com/Ad115/python-treet
Author: Ad115
Author-email: a.garcia230395@gmail.com
License: UNKNOWN
Project-URL: Say Thanks!, https://saythanks.io/to/Ad115
Project-URL: Documentation, https://github.com/Ad115/python-treet
Project-URL: Author, https://agargar.wordpress.com/
Keywords: tree hierarchical generic newick traverse reduce
Platform: UNKNOWN
Classifier: Development Status :: 4 - Beta
Classifier: Intended Audience :: Information Technology
Classifier: Intended Audience :: Science/Research
Classifier: Intended Audience :: Education
Classifier: Intended Audience :: Developers
Classifier: Topic :: Software Development
Classifier: Topic :: Software Development :: Libraries
Classifier: Topic :: Scientific/Engineering :: Artificial Life
Classifier: Topic :: Scientific/Engineering :: Bio-Informatics
Classifier: Topic :: Scientific/Engineering :: Medical Science Apps.
Classifier: Topic :: Text Processing
Classifier: Topic :: Utilities
Classifier: License :: OSI Approved :: MIT License
Classifier: Programming Language :: Python :: 3 :: Only
Provides-Extra: dev
Requires-Dist: pytest ; extra == 'dev'
Requires-Dist: hypothesis ; extra == 'dev'
Requires-Dist: coverage ; extra == 'dev'
Requires-Dist: mypy ; extra == 'dev'
